anytime/AnytimeAlgorithm1.py
anytime/AnytimeAlgorithm2.py
anytime/AnytimeAlgorithmTest.py
anytime/__init__.py
anytime-1.0.0.dev1.dist-info/DESCRIPTION.rst
anytime-1.0.0.dev1.dist-info/METADATA
anytime-1.0.0.dev1.dist-info/RECORD
anytime-1.0.0.dev1.dist-info/WHEEL
anytime-1.0.0.dev1.dist-info/metadata.json
anytime-1.0.0.dev1.dist-info/top_level.txt
