Metadata-Version: 2.0
Name: anytime
Version: 1.0.0.dev1
Summary: Anytime algorithms in Python
Home-page: https://github.com/erelsgl/anytime.py
Author: Erel Segal-Halevi
Author-email: erelsgl@gmail.com
License: UNKNOWN
Keywords: anytime algorithms
Platform: UNKNOWN
Classifier: Development Status :: 2 - Pre-Alpha
Classifier: Intended Audience :: Developers
Classifier: Topic :: Software Development
Classifier: License :: OSI Approved :: GNU General Public License (GPL)
Classifier: Programming Language :: Python :: 3
Classifier: Programming Language :: Python :: 3.5
Classifier: Programming Language :: Python :: 3.6
